iexfinance/__init__.py
iexfinance/base.py
iexfinance/account/__init__.py
iexfinance/account/base.py
iexfinance/altdata/__init__.py
iexfinance/altdata/base.py
iexfinance/apidata/__init__.py
iexfinance/apidata/base.py
iexfinance/data_apis/__init__.py
iexfinance/data_apis/data_points.py
iexfinance/data_apis/time_series.py
iexfinance/iexdata/__init__.py
iexfinance/iexdata/base.py
iexfinance/refdata/__init__.py
iexfinance/refdata/base.py
iexfinance/stocks/__init__.py
iexfinance/stocks/base.py
iexfinance/stocks/collections.py
iexfinance/stocks/historical.py
iexfinance/stocks/ipocalendar.py
iexfinance/stocks/marketvolume.py
iexfinance/stocks/movers.py
iexfinance/stocks/options.py
iexfinance/stocks/sectorperformance.py
iexfinance/stocks/todayearnings.py
iexfinance/tests/__init__.py
iexfinance/tests/conftest.py
iexfinance/tests/fixtures.py
iexfinance/tests/test_account.py
iexfinance/tests/test_altdata.py
iexfinance/tests/test_apidata.py
iexfinance/tests/test_auth.py
iexfinance/tests/test_base.py
iexfinance/tests/test_iexdata.py
iexfinance/tests/test_refdata.py
iexfinance/tests/test_utils.py
iexfinance/tests/data_apis/__init__.py
iexfinance/tests/data_apis/test_data_points.py
iexfinance/tests/data_apis/test_time_series.py
iexfinance/tests/stocks/__init__.py
iexfinance/tests/stocks/test_collections.py
iexfinance/tests/stocks/test_earnings_today.py
iexfinance/tests/stocks/test_eod_options.py
iexfinance/tests/stocks/test_field_methods.py
iexfinance/tests/stocks/test_fundamentals.py
iexfinance/tests/stocks/test_historical.py
iexfinance/tests/stocks/test_ipo_calendar.py
iexfinance/tests/stocks/test_market_movers.py
iexfinance/tests/stocks/test_market_volume.py
iexfinance/tests/stocks/test_news.py
iexfinance/tests/stocks/test_prices.py
iexfinance/tests/stocks/test_profiles.py
iexfinance/tests/stocks/test_research.py
iexfinance/tests/stocks/test_sector_performance.py
iexfinance/tests/stocks/test_stocks_base.py
iexfinance/utils/__init__.py
iexfinance/utils/exceptions.py
iexfinance-0.5.0.dist-info/LICENSE.txt
iexfinance-0.5.0.dist-info/METADATA
iexfinance-0.5.0.dist-info/WHEEL
iexfinance-0.5.0.dist-info/top_level.txt
iexfinance-0.5.0.dist-info/RECORD
