Metadata-Version: 2.1
Name: iexfinance
Version: 0.5.0
Summary: Python module to get stock data from IEX Cloud and IEX API 1.0
Home-page: https://github.com/addisonlynch/iexfinance
Author: Addison Lynch
Author-email: ahljunk@gmail.com
License: Apache
Download-URL: https://github.com/addisonlynch/iexfinance/releases
Keywords: stocks market finance iex quotes shares currency
Platform: UNKNOWN
Classifier: Development Status :: 4 - Beta
Classifier: Intended Audience :: Developers
Classifier: Intended Audience :: Financial and Insurance Industry
Classifier: Topic :: Office/Business :: Financial :: Investment
Classifier: Topic :: Software Development :: Libraries :: Python Modules
Classifier: Operating System :: OS Independent
Classifier: License :: OSI Approved :: Apache Software License
Classifier: Programming Language :: Python
Classifier: Programming Language :: Python :: 3
Classifier: Programming Language :: Python :: 3.4
Classifier: Programming Language :: Python :: 3.5
Classifier: Programming Language :: Python :: 3.6
